{
  "_prompt_version": "marxist-v0.1-2026-04-30",
  "n": 102,
  "annotation": {
    "gist": "本段记录列宁对李普曼的批驳。李普曼通过提出一系列具体问题，试图挖苦“保障少数民族权利”这一原则，并以此论证需要一个更“积极的”民族纲领。",
    "plain_rewrite": "李普曼想用这个问题来挖苦这个原则。他问道：我们怎么才能知道哪些是少数民族的权利呢？比如，民族学校里使用“自己的教学大纲”的权利，算不算这些权利的一部分？少数民族要达到多大规模，才有权设立自己的法院、拥有自己的官吏、开办使用本族语言的学校呢？李普曼想用这些问题来证明，必须有一个“积极的”民族纲领。",
    "block_type": "author_text",
    "length_policy": "normal_paragraph",
    "sentences": [
      {
        "sid": "p102s1",
        "plain": "李普曼想用这个问题来挖苦这个原则。他问道：我们怎么才能知道哪些是少数民族的权利呢？比如，民族学校里使用“自己的教学大纲”的权利，算不算这些权利的一部分？",
        "speaker": "quoted_opponent",
        "stance": "criticized",
        "notes": [
          {
            "surface": "公式",
            "type": "concept",
            "target": null,
            "modern": "指列宁在前文提出的“保障少数民族权利”的原则。",
            "highlight": "term"
          },
          {
            "surface": "李普曼",
            "type": "polemic_ref",
            "target": null,
            "modern": "弗·李普曼，当时俄国社会民主工党内的民族文化自治论者，列宁的论战对象。",
            "highlight": "polemic"
          },
          {
            "surface": "少数民族的权利",
            "type": "concept",
            "target": null,
            "modern": "指在多民族国家中，非主体民族应享有的平等权利，是列宁与论敌争论的核心概念。",
            "highlight": "term"
          },
          {
            "surface": "怎么才能知道什么是少数民族的权利呢？",
            "type": "quote",
            "target": null,
            "modern": "这是李普曼提出的反问，意在质疑“少数民族权利”概念的模糊性。",
            "highlight": "quote"
          }
        ]
      },
      {
        "sid": "p102s2",
        "plain": "少数民族要达到多大规模，才有权设立自己的法院、拥有自己的官吏、开办使用本族语言的学校呢？",
        "speaker": "quoted_opponent",
        "stance": "criticized",
        "notes": [
          {
            "surface": "法院",
            "type": "concept",
            "target": null,
            "modern": "李普曼举例的具体权利之一，指少数民族建立独立司法机构的权利。",
            "highlight": "term"
          },
          {
            "surface": "官吏",
            "type": "concept",
            "target": null,
            "modern": "李普曼举例的具体权利之一，指少数民族拥有本民族行政人员的权利。",
            "highlight": "term"
          },
          {
            "surface": "学校",
            "type": "concept",
            "target": null,
            "modern": "李普曼举例的具体权利之一，指少数民族使用本民族语言进行教育的权利。",
            "highlight": "term"
          }
        ]
      },
      {
        "sid": "p102s3",
        "plain": "李普曼想用这些问题来证明，必须有一个“积极的”民族纲领。",
        "speaker": "quoted_opponent",
        "stance": "criticized",
        "notes": [
          {
            "surface": "积极的",
            "type": "polemic_ref",
            "target": null,
            "modern": "李普曼所主张的，认为仅保障权利不够，还需要主动构建民族文化体系的纲领。列宁在批判这种观点。",
            "highlight": "polemic"
          },
          {
            "surface": "民族纲领",
            "type": "concept",
            "target": null,
            "modern": "指关于如何处理民族问题的政治主张和行动计划。",
            "highlight": "term"
          }
        ]
      }
    ]
  }
}