{
  "_prompt_version": "marxist-v0.3-2026-04-30-codex-fixed",
  "n": 4,
  "annotation": {
    "block_type": "author_text",
    "gist": "本段分析6月18日游行示威的政治意义，指出它清晰地揭示了各阶级的力量对比与相互关系，从而提升了民众的觉悟。",
    "importance_score": 2,
    "importance_reason": "支撑核心论点，具体阐释前段所称“转折点”的内涵，即阶级力量格局的清晰化。",
    "argument_role": "continues",
    "argument_link": "承接上段关于6月18日是革命史转折点的论断，具体说明这一转折体现在阶级力量对比的清晰显现上。",
    "paragraph_gates": {
      "needs_prereading": false,
      "prereading_reason": "none",
      "needs_hard_sentence": false,
      "hard_sentence_reason": "none",
      "needs_polemic": false,
      "polemic_reason": "none"
    },
    "prereading_refs": [],
    "prereading_inline": [],
    "hard_sentences": [],
    "polemic_in_paragraph": {
      "is_polemical": false,
      "target": null,
      "their_view": null,
      "author_response": null,
      "polemic_kind": null,
      "confidence": null
    },
    "sentences": [
      {
        "sid": "p4s1",
        "speaker": "author",
        "stance": "self",
        "notes": [
          {
            "surface": "各阶级",
            "type": "concept",
            "modern": "在马克思主义分析框架下，指社会中因对生产资料占有关系不同而形成的不同集团。",
            "highlight": "term",
            "confidence": "high",
            "source_basis": "whitelist",
            "sense_id": "class_marxist"
          },
          {
            "surface": "斗争",
            "type": "concept",
            "modern": "此处特指不同阶级之间为争夺政治权力和经济利益而进行的对抗。",
            "highlight": "term",
            "confidence": "high",
            "source_basis": "whitelist",
            "sense_id": "class_struggle"
          }
        ]
      }
    ]
  }
}