{
  "_prompt_version": "marxist-v0.1-2026-04-30",
  "n": 112,
  "annotation": {
    "gist": "本段指出德意志银行在银行网络中的持续参与，作为列宁分析帝国主义金融资本体系的一个具体例证。",
    "plain_rewrite": "德意志银行一直参与其中。",
    "block_type": "author_text",
    "length_policy": "normal_paragraph",
    "sentences": [
      {
        "sid": "p112s1",
        "plain": "德意志银行一直参与其中。",
        "speaker": "author",
        "stance": "self",
        "notes": [
          {
            "surface": "德意志银行",
            "type": "org",
            "target": null,
            "modern": "德国主要银行，在19世纪末20世纪初是金融资本的代表，参与帝国主义扩张和银行间网络。",
            "highlight": "term"
          }
        ]
      }
    ]
  }
}