{
  "_prompt_version": "marxist-v0.1-2026-04-30",
  "n": 104,
  "annotation": {
    "gist": "标明恩格斯为《资本论》第三卷所作增补的标题及页码范围。",
    "plain_rewrite": "弗里德里希·恩格斯为《资本论》第三卷所作的增补，位于第1003页至第1030页。",
    "block_type": "title",
    "length_policy": "preserve",
    "sentences": [
      {
        "sid": "p104s1",
        "plain": "弗里德里希·恩格斯为《资本论》第三卷所作的增补，位于第1003页至第1030页。",
        "speaker": "author",
        "stance": "self",
        "notes": [
          {
            "surface": "弗·恩格斯",
            "type": "person",
            "target": null,
            "modern": "弗里德里希·恩格斯，马克思的亲密战友，共同创立了马克思主义，并在马克思逝世后整理出版了《资本论》后几卷。",
            "highlight": "term"
          },
          {
            "surface": "《资本论》第三卷",
            "type": "work",
            "target": null,
            "modern": "马克思的主要经济学著作《资本论》的第三卷，主要分析资本主义生产的总过程，恩格斯根据马克思遗稿整理编辑而成。",
            "highlight": "term"
          },
          {
            "surface": "增补",
            "type": "concept",
            "target": null,
            "modern": "指恩格斯在整理马克思遗稿时，为补充、说明或发展马克思的观点而添加的内容。",
            "highlight": "term"
          }
        ]
      }
    ]
  }
}