{
  "_prompt_version": "marxist-v0.1-2026-04-30",
  "n": 185,
  "annotation": {
    "gist": "本段以蒲鲁东的《贫困的哲学》为例，具体说明前文所描述的资产阶级社会主义或改良社会主义。",
    "plain_rewrite": "蒲鲁东的《贫困的哲学》就是这种社会主义的一个例子。",
    "block_type": "author_text",
    "length_policy": "normal_paragraph",
    "sentences": [
      {
        "sid": "p185s1",
        "plain": "蒲鲁东的《贫困的哲学》就是这种社会主义的一个例子。",
        "speaker": "author",
        "stance": "self",
        "notes": [
          {
            "surface": "蒲魯東",
            "type": "person",
            "target": null,
            "modern": "法国社会主义思想家皮埃尔-约瑟夫·蒲鲁东，无政府主义理论家",
            "highlight": "term"
          },
          {
            "surface": "貧困底哲學",
            "type": "work",
            "target": null,
            "modern": "蒲鲁东1846年出版的著作《贫困的哲学》",
            "highlight": "term"
          },
          {
            "surface": "底",
            "type": "concept_archaic_translation",
            "target": null,
            "modern": "相当于现代汉语的'的'，表示所属关系",
            "highlight": "archaic"
          },
          {
            "surface": "這樣社會主義",
            "type": "polemic_ref",
            "target": null,
            "modern": "指前文所述的资产阶级社会主义或改良社会主义，主张通过改良调和阶级矛盾",
            "highlight": "polemic"
          }
        ]
      }
    ]
  }
}