{
  "_prompt_version": "marxist-v0.3-2026-04-30-codex-fixed",
  "n": 925,
  "annotation": {
    "block_type": "narrative",
    "gist": "记述马克思与恩格斯在布鲁塞尔落实建立国际通讯组织的决定。",
    "importance_score": 1,
    "importance_reason": "作为前段决策的具体执行步骤，属于叙事过渡。",
    "argument_role": "continues",
    "argument_link": "承接上段关于创立国际组织的决定，具体说明其在布鲁塞尔的初步实践。",
    "paragraph_gates": {
      "needs_prereading": false,
      "prereading_reason": "none",
      "needs_hard_sentence": false,
      "hard_sentence_reason": "none",
      "needs_polemic": false,
      "polemic_reason": "none"
    },
    "prereading_refs": [],
    "prereading_inline": [],
    "hard_sentences": [],
    "polemic_in_paragraph": {
      "is_polemical": false,
      "target": null,
      "their_view": null,
      "author_response": null,
      "polemic_kind": null,
      "confidence": null
    },
    "sentences": [
      {
        "sid": "p925s1",
        "speaker": "author",
        "stance": "self",
        "notes": []
      }
    ]
  }
}