{
  "_prompt_version": "marxist-v0.1-2026-04-30",
  "n": 6,
  "annotation": {
    "gist": "恩格斯用辩证法观点批判形而上学的机械世界观，并讽刺其拥护者。",
    "plain_rewrite": "量变引起质变的规律，恰恰是那种“机械的”世界观所忽视的，它只看到量的变化，却不懂量变如何改变事物的质。这是那些绅士们从来没有闻到过的道理！",
    "block_type": "author_text",
    "length_policy": "normal_paragraph",
    "sentences": [
      {
        "sid": "p6s1",
        "plain": "量变引起质变的规律，恰恰是那种“机械的”世界观所忽视的，它只看到量的变化，却不懂量变如何改变事物的质。",
        "speaker": "author",
        "stance": "self",
        "notes": [
          {
            "surface": "量到质的转化",
            "type": "concept",
            "target": null,
            "modern": "指事物数量的变化积累到一定程度，必然引起根本性质的变化，是辩证法的基本规律之一。",
            "highlight": "term"
          },
          {
            "surface": "“机械的”世界观",
            "type": "concept",
            "target": null,
            "modern": "指形而上学的思维方式，它孤立、静止、片面地看问题，否认事物内部的矛盾和质变。",
            "highlight": "term"
          }
        ]
      },
      {
        "sid": "p6s2",
        "plain": "这是那些绅士们从来没有闻到过的道理！",
        "speaker": "author",
        "stance": "self",
        "notes": [
          {
            "surface": "绅士们",
            "type": "polemic_ref",
            "target": null,
            "modern": "讽刺性地指代那些坚持形而上学机械世界观、反对辩证法的学者或思想家。",
            "highlight": "polemic"
          }
        ]
      }
    ]
  }
}