{
  "_prompt_version": "marxist-v0.3-2026-04-30-codex-fixed",
  "n": 32,
  "annotation": {
    "block_type": "author_text",
    "gist": "叙述作者与同伴在巴黎重聚，并起草了一份在德国广泛传播的文件。",
    "importance_score": 1,
    "importance_reason": "过渡段，连接前文事件与后文文件内容。",
    "argument_role": "none",
    "argument_link": null,
    "paragraph_gates": {
      "needs_prereading": true,
      "prereading_reason": "cross_ref_pronoun",
      "needs_hard_sentence": false,
      "hard_sentence_reason": "none",
      "needs_polemic": false,
      "polemic_reason": "none"
    },
    "prereading_refs": [],
    "prereading_inline": [
      {
        "topic": "共产主义者同盟成员",
        "explain": "本段'我们大家'指共产主义者同盟的领导成员，他们在1848年二月革命后重组组织并流亡，此处指他们在巴黎重聚。",
        "why_needed": "cross_ref_pronoun",
        "confidence": "high",
        "source_basis": "known_history"
      }
    ],
    "hard_sentences": [],
    "polemic_in_paragraph": {
      "is_polemical": false,
      "target": null,
      "their_view": null,
      "author_response": null,
      "polemic_kind": null,
      "confidence": null
    },
    "sentences": [
      {
        "sid": "p32s1",
        "speaker": "author",
        "stance": "self",
        "notes": []
      },
      {
        "sid": "p32s2",
        "speaker": "author",
        "stance": "self",
        "notes": []
      }
    ]
  }
}