{
  "_prompt_version": "marxist-v0.3-2026-04-30-codex-fixed",
  "n": 91,
  "annotation": {
    "block_type": "author_text",
    "gist": "分析资本主义上升时期民族斗争的阶级性质，指出其本质是资产阶级之间的斗争，即使有无产阶级参与也仅是表面现象。",
    "importance_score": 2,
    "importance_reason": "为全文的民族理论提供阶级分析基础，是论证民族问题实质的关键环节。",
    "argument_role": "continues",
    "argument_link": "承接上段对民族运动形式与性质的概述，深入剖析其背后的阶级驱动力与实质。",
    "paragraph_gates": {
      "needs_prereading": false,
      "prereading_reason": "none",
      "needs_hard_sentence": false,
      "hard_sentence_reason": "none",
      "needs_polemic": false,
      "polemic_reason": "none"
    },
    "prereading_refs": [],
    "prereading_inline": [],
    "hard_sentences": [],
    "polemic_in_paragraph": {
      "is_polemical": false,
      "target": null,
      "their_view": null,
      "author_response": null,
      "polemic_kind": null,
      "confidence": null
    },
    "sentences": [
      {
        "sid": "p91s1",
        "speaker": "author",
        "stance": "self",
        "notes": []
      },
      {
        "sid": "p91s2",
        "speaker": "author",
        "stance": "self",
        "notes": []
      },
      {
        "sid": "p91s3",
        "speaker": "author",
        "stance": "self",
        "notes": []
      }
    ]
  }
}