{
  "_prompt_version": "marxist-v0.3-2026-04-30-codex-fixed",
  "n": 39,
  "annotation": {
    "block_type": "author_text",
    "gist": "本段陈述巴黎无产阶级在遭受重大挫折后需要休养生息的客观判断，并随即指出布朗基主义者对此持有相反的战略主张。",
    "importance_score": 2,
    "importance_reason": "本段是作者批判布朗基主义战略路线的起点，通过对比客观形势与主观盲动，为后续的论战奠定基础。",
    "argument_role": "contrasts",
    "argument_link": "承接上段对某些流亡者自比布鲁土斯的讽刺，本段具体指出布朗基主义者在革命时机判断上与客观形势的尖锐对立。",
    "paragraph_gates": {
      "needs_prereading": false,
      "prereading_reason": "none",
      "needs_hard_sentence": false,
      "hard_sentence_reason": "none",
      "needs_polemic": true,
      "polemic_reason": "explicit_target"
    },
    "prereading_refs": [],
    "prereading_inline": [],
    "hard_sentences": [],
    "polemic_in_paragraph": {
      "is_polemical": false,
      "target": null,
      "their_view": null,
      "author_response": null,
      "polemic_kind": null,
      "confidence": null
    },
    "sentences": [
      {
        "sid": "p39s1",
        "speaker": "author",
        "stance": "self",
        "notes": []
      },
      {
        "sid": "p39s2",
        "speaker": "quoted_opponent",
        "stance": "criticized",
        "notes": []
      }
    ]
  },
  "_validate_passes": [
    {
      "version": "v0.3-validate",
      "stats": {
        "notes_kept": 0,
        "notes_dropped": 0,
        "hs_kept": 0,
        "hs_dropped": 0,
        "polemic_zeroed": 1,
        "para_eval_issues": 0
      },
      "reasons": [
        "polemic:their_view_eq_response_5gram"
      ]
    }
  ]
}