{
  "_prompt_version": "marxist-v0.1-2026-04-30",
  "n": 4,
  "annotation": {
    "gist": "本段以军队历史为例，具体论证生产力与社会关系之间的联系，并指出军队在经济发展中扮演了重要角色。",
    "plain_rewrite": "军队的历史比任何其他事物都更清楚地证明了我们关于生产力和社会关系之间联系的看法是正确的。总的来说，军队在经济发展中起着重要作用。举几个例子：薪金制度最初完全是在古代军队中发展起来的。同样，罗马人的“军营财产权”是法律上第一次承认非家长拥有的动产。“军工工匠”工会是行会制度的开端。大规模使用机器也是首先在军队中开始的。甚至金属的特殊价值和它作为货币的用途，看来最初（在格林时期之后）也是以它在军事上的作用为基础的。部门内部的分工也是首先在军队里实行的。此外，军队的历史非常明显地概括了市民社会的全部历史。如果今后有时间，你应当从这个角度去探讨这个问题。",
    "block_type": "author_text",
    "length_policy": "normal_paragraph",
    "sentences": [
      {
        "sid": "p4s1",
        "plain": "军队的历史比任何其他事物都更清楚地证明了我们关于生产力和社会关系之间联系的看法是正确的。",
        "speaker": "author",
        "stance": "self",
        "notes": [
          {
            "surface": "生产力",
            "type": "concept",
            "target": null,
            "modern": "人类改造自然的能力，是社会发展的最终决定力量。",
            "highlight": "term"
          },
          {
            "surface": "社会关系",
            "type": "concept",
            "target": null,
            "modern": "人们在社会生产和生活过程中形成的各种关系，核心是生产关系。",
            "highlight": "term"
          }
        ]
      },
      {
        "sid": "p4s2",
        "plain": "总的来说，军队在经济发展中起着重要作用。",
        "speaker": "author",
        "stance": "self",
        "notes": []
      },
      {
        "sid": "p4s3",
        "plain": "举几个例子：薪金制度最初完全是在古代军队中发展起来的。",
        "speaker": "author",
        "stance": "self",
        "notes": []
      },
      {
        "sid": "p4s4",
        "plain": "同样，罗马人的“军营财产权”是法律上第一次承认非家长拥有的动产。",
        "speaker": "author",
        "stance": "self",
        "notes": [
          {
            "surface": "peculium castrense",
            "type": "concept",
            "target": null,
            "modern": "拉丁语，指罗马法中士兵对其在军营中获得的财产享有的特殊财产权，区别于家庭财产。",
            "highlight": "term"
          }
        ]
      },
      {
        "sid": "p4s5",
        "plain": "“军工工匠”工会是行会制度的开端。",
        "speaker": "author",
        "stance": "self",
        "notes": [
          {
            "surface": "fabri",
            "type": "concept",
            "target": null,
            "modern": "拉丁语，指古罗马军队中负责制造和修理武器装备的工匠团体。",
            "highlight": "term"
          }
        ]
      },
      {
        "sid": "p4s6",
        "plain": "大规模使用机器也是首先在军队中开始的。",
        "speaker": "author",
        "stance": "self",
        "notes": []
      },
      {
        "sid": "p4s7",
        "plain": "甚至金属的特殊价值和它作为货币的用途，看来最初（在格林时期之后）也是以它在军事上的作用为基础的。",
        "speaker": "author",
        "stance": "self",
        "notes": [
          {
            "surface": "格林时期时代",
            "type": "event",
            "target": null,
            "modern": "指德国历史上的“民族大迁徙时期”（约公元3-6世纪），马克思用此指代一个较早的历史阶段。",
            "highlight": null
          }
        ]
      },
      {
        "sid": "p4s8",
        "plain": "部门内部的分工也是首先在军队里实行的。",
        "speaker": "author",
        "stance": "self",
        "notes": []
      },
      {
        "sid": "p4s9",
        "plain": "此外，军队的历史非常明显地概括了市民社会的全部历史。",
        "speaker": "author",
        "stance": "self",
        "notes": [
          {
            "surface": "市民社会",
            "type": "concept",
            "target": null,
            "modern": "马克思理论中指与国家相对的私人生活领域，特别是物质交往关系的总和。",
            "highlight": "term"
          }
        ]
      },
      {
        "sid": "p4s10",
        "plain": "如果今后有时间，你应当从这个角度去探讨这个问题。",
        "speaker": "author",
        "stance": "self",
        "notes": []
      }
    ]
  }
}