{
  "_prompt_version": "marxist-v0.3-2026-04-30-codex-fixed",
  "n": 63,
  "annotation": {
    "block_type": "author_text",
    "gist": "本段论证反革命势力依靠经济自由维持统治，若放弃无产阶级专政而实行各派主张的自由平等，将导致类似混乱局面。",
    "importance_score": 2,
    "importance_reason": "通过具体分析高尔察克的统治基础，论证放弃无产阶级专政的危险后果，是支撑核心论点的例证。",
    "argument_role": "continues",
    "argument_link": "承接上段对高尔察克经济基础的分析，进一步推论放弃无产阶级专政的普遍后果，并以乌克兰的混乱为例证。",
    "paragraph_gates": {
      "needs_prereading": false,
      "prereading_reason": "none",
      "needs_hard_sentence": false,
      "hard_sentence_reason": "none",
      "needs_polemic": true,
      "polemic_reason": "explicit_target"
    },
    "prereading_refs": [],
    "prereading_inline": [],
    "hard_sentences": [],
    "polemic_in_paragraph": {
      "is_polemical": true,
      "target": "民主派、社会革命党人、左派孟什维克、无政府主义者",
      "their_view": "他们主张实行不区分阶级的普遍自由和平等，认为这样能实现民主。",
      "author_response": "列宁指出这种主张实质上是放弃无产阶级专政，会导致反革命势力和各地匪帮趁机作乱。",
      "polemic_kind": "refutes_premise",
      "confidence": "high"
    },
    "sentences": [
      {
        "sid": "p63s1",
        "speaker": "author",
        "stance": "self",
        "notes": []
      },
      {
        "sid": "p63s2",
        "speaker": "author",
        "stance": "self",
        "notes": []
      },
      {
        "sid": "p63s3",
        "speaker": "author",
        "stance": "self",
        "notes": []
      }
    ]
  }
}