{
  "_prompt_version": "marxist-v0.1-2026-04-30",
  "n": 158,
  "annotation": {
    "gist": "本段承接前文关于无产阶级专政任务的论述，具体指出其军事任务：必须建立革命武装和军队，以对抗外部敌人和帝国主义。",
    "plain_rewrite": "用武装力量保卫革命，组建革命军队，以此来对抗外部敌人，对抗帝国主义。",
    "block_type": "author_text",
    "length_policy": "normal_paragraph",
    "sentences": [
      {
        "sid": "p158s1",
        "plain": "用武装力量保卫革命，组建革命军队，以此来对抗外部敌人，对抗帝国主义。",
        "speaker": "author",
        "stance": "self",
        "notes": [
          {
            "surface": "革命武装",
            "type": "concept",
            "target": null,
            "modern": "指无产阶级掌握的武装力量，是进行暴力革命和巩固无产阶级专政的必要工具。",
            "highlight": "term"
          },
          {
            "surface": "帝国主义",
            "type": "concept",
            "target": null,
            "modern": "指资本主义发展的最高阶段，其特征是垄断、金融资本输出和瓜分世界。在列宁主义语境中，是无产阶级革命的主要外部敌人。",
            "highlight": "term"
          }
        ]
      }
    ]
  }
}