{
  "_prompt_version": "marxist-v0.1-2026-04-30",
  "n": 29,
  "annotation": {
    "gist": "本段是恩格斯对罗亚尔河谷的实地观察，描述了从沙多卢到姆比埃尔沿途的地理环境、物产与景观，为后文遇到亚尔萨斯商队做铺垫。",
    "plain_rewrite": "从沙多卢经勒-博尔德到姆比埃尔的路上，就几乎看不到那条充满浪漫色彩的罗亚尔河了。这条路在离河两三里远的丘陵间穿过，从那里远远望去，只能偶尔瞥见被太阳照得闪闪发光的罗亚尔河水。这一带盛产葡萄酒、谷物和水果，而靠近河岸的地方，则是一片绿油油的草地。这个没有树林的河谷，周围全是波浪般起伏的丘陵，看上去总觉得相当单调。",
    "block_type": "author_text",
    "length_policy": "normal_paragraph",
    "sentences": [
      {
        "sid": "p29s1",
        "plain": "从沙多卢经勒-博尔德到姆比埃尔的路上，就几乎看不到那条充满浪漫色彩的罗亚尔河了。",
        "speaker": "author",
        "stance": "self",
        "notes": []
      },
      {
        "sid": "p29s2",
        "plain": "这条路在离河两三里远的丘陵间穿过，从那里远远望去，只能偶尔瞥见被太阳照得闪闪发光的罗亚尔河水。",
        "speaker": "author",
        "stance": "self",
        "notes": [
          {
            "surface": "偶而",
            "type": "concept_archaic_translation",
            "target": null,
            "modern": "现代汉语通常写作“偶尔”，表示间或、有时候。",
            "highlight": "archaic"
          }
        ]
      },
      {
        "sid": "p29s3",
        "plain": "这一带盛产葡萄酒、谷物和水果，而靠近河岸的地方，则是一片绿油油的草地。",
        "speaker": "author",
        "stance": "self",
        "notes": []
      },
      {
        "sid": "p29s4",
        "plain": "这个没有树林的河谷，周围全是波浪般起伏的丘陵，看上去总觉得相当单调。",
        "speaker": "author",
        "stance": "self",
        "notes": []
      }
    ]
  }
}