{
  "_prompt_version": "marxist-v0.3-2026-04-30-codex-fixed",
  "n": 10,
  "annotation": {
    "block_type": "author_text",
    "gist": "承接上文要求，以染坊为例说明错误罚款现象，并援引法律原则指出工人不应为工头失误承担损失。",
    "importance_score": 1,
    "importance_reason": "通过具体案例支撑前文提出的公开扣款记录要求，揭示工厂管理中的不公现象。",
    "argument_role": "example",
    "argument_link": "本段用染坊的具体案例，说明前文提出的公开扣款记录要求的必要性，展示错误罚款的实际存在。",
    "paragraph_gates": {
      "needs_prereading": false,
      "prereading_reason": "none",
      "needs_hard_sentence": false,
      "hard_sentence_reason": "none",
      "needs_polemic": false,
      "polemic_reason": "none"
    },
    "prereading_refs": [],
    "prereading_inline": [],
    "hard_sentences": [],
    "polemic_in_paragraph": {
      "is_polemical": false,
      "target": null,
      "their_view": null,
      "author_response": null,
      "polemic_kind": null,
      "confidence": null
    },
    "sentences": [
      {
        "sid": "p10s1",
        "speaker": "author",
        "stance": "self",
        "notes": []
      },
      {
        "sid": "p10s2",
        "speaker": "author",
        "stance": "self",
        "notes": []
      }
    ]
  }
}