{
  "_prompt_version": "marxist-v0.1-2026-04-30",
  "n": 55,
  "annotation": {
    "gist": "本段是马克思对国民经济学观点的总结性批判，指出在资本主义制度下，工人阶级的生存状况是悲惨的。",
    "plain_rewrite": "那些超出这个数量的工人，注定会死亡。",
    "block_type": "author_text",
    "length_policy": "normal_paragraph",
    "sentences": [
      {
        "sid": "p55s1",
        "plain": "那些超出这个数量的工人，注定会死亡。",
        "speaker": "author",
        "stance": "self",
        "notes": [
          {
            "surface": "注定会死亡",
            "type": "concept",
            "target": null,
            "modern": "指工人阶级在资本主义制度下的悲惨命运，生存状况恶化。",
            "highlight": "term"
          },
          {
            "surface": "超过这个人数的部分",
            "type": "polemic_ref",
            "target": null,
            "modern": "本句批判国民经济学将工人视为生产要素，忽视其生存困境的观点。",
            "highlight": "polemic"
          }
        ]
      }
    ]
  }
}