{
  "_prompt_version": "marxist-v0.1-2026-04-30",
  "source_url": "https://www.marxists.org/chinese/lenin/marxist.org-chinese-lenin-191405.htm",
  "author": "lenin",
  "subdoc_id": "main",
  "label": "腐蚀工人的精致的民族主义",
  "title": "腐蚀工人的精致的民族主义",
  "year": 1914,
  "meta": {
    "tldr_modern": "列宁批评了那种以保护“民族文化”为名，主张按民族划分教育事业、分裂工人组织的“精致的民族主义”思潮，强调工人阶级必须在统一的组织中团结起来，反对一切形式的民族分裂。",
    "tldr_extended": [
      "资产阶级和地主在暴力镇压之外，越来越多地利用“精致的民族主义”思想来分化工人阶级。",
      "这种“精致的民族主义”以保护民族文化、民族自决为借口，鼓吹按民族分裂工人事业和组织。",
      "马克思主义者主张各民族和语言的完全平等，但坚决反对“民族文化自治”这类将教育事业按民族分割的计划。",
      "无产阶级国际主义要求各民族工人在统一的无产阶级组织中融合，共同反对民族资产阶级。",
      "文章驳斥了将承认本民族语言教学权与“民族文化自治”混为一谈的错误观点。"
    ],
    "historical_context": "本文写于1914年5月，第一次世界大战爆发前夕。当时欧洲民族主义情绪高涨，俄国工人运动内部也面临民族问题的复杂争论。列宁在《真理之路报》上发表此文，旨在批判党内和工人运动中出现的、以民族文化为旗号的分裂倾向，特别是针对崩得、取消派等派别所主张的“民族文化自治”纲领，以维护无产阶级的国际团结和统一斗争。",
    "polemic_targets": [
      {
        "target_type": "school",
        "target_id": "bund",
        "target_name_zh": "崩得分子",
        "view_being_refuted": "主张“民族文化自治”，即把教育事业从国家管理中分出来，交给按民族划分的联盟管理，以此作为解决民族问题的方案。",
        "author_position": "列宁认为这是腐蚀和分化工人阶级的精致的民族主义计划，马克思主义者坚决斥责并反对这种将教育事业按民族分割的做法。"
      },
      {
        "target_type": "school",
        "target_id": "liquidators",
        "target_name_zh": "取消派分子",
        "view_being_refuted": "与崩得分子等一同被列宁归为鼓吹“精致的民族主义”和“民族文化自治”的小资产阶级集团。",
        "author_position": "列宁认为他们与崩得分子一样，在用资产阶级思想分化工人。"
      },
      {
        "target_type": "school",
        "target_id": "narodniks",
        "target_name_zh": "民粹派分子",
        "view_being_refuted": "与崩得分子、取消派分子一同被列宁列为“精致的民族主义”计划的提出者。",
        "author_position": "列宁认为他们属于各种小资产阶级集团，其主张与无产阶级国际主义相悖。"
      },
      {
        "target_type": "person",
        "target_id": "v_o_lady",
        "target_name_zh": "符·奥·女士",
        "view_being_refuted": "在《北方工人报》上宣称“拥护真理派”否认用本民族语言教学的权利，将承认语言权利与“民族文化自治”混为一谈。",
        "author_position": "列宁斥责这是一种绝大的诬蔑和绝顶无知的表现，指出真理派比任何人都更彻底地承认本民族语言的充分权利。"
      },
      {
        "target_type": "trend",
        "target_id": "cultural_national_autonomy",
        "target_name_zh": "“民族文化自治”思潮",
        "view_being_refuted": "主张将教育事业从国家管理中分离出来，交给按民族划分的联盟管理，以此实现民族平等。",
        "author_position": "列宁认为这是腐蚀工人的精致的民族主义，马克思主义者主张民族语言平等，但坚持国家机关、教育政策的统一和工人组织的统一。"
      }
    ],
    "key_concepts": [
      "nationalism",
      "proletarian_internationalism",
      "cultural_national_autonomy",
      "class_struggle",
      "national_question",
      "workers_movement"
    ],
    "key_persons": [
      "lenin",
      "v_o_lady"
    ],
    "key_works": [
      "pravda_puti",
      "severny_rabochy",
      "kolokol_zhurnal"
    ],
    "key_events": [],
    "key_orgs": [
      "bund",
      "liquidators",
      "narodniks"
    ],
    "categories": [
      "polemic",
      "scientific_socialism"
    ],
    "primary_category": "polemic",
    "author_period": "lenin_1900s_1910s",
    "historical_period": "pre_ww1_socialdemocracy",
    "thematic_domain": [
      "national_question",
      "workers_movement"
    ],
    "provenance": {
      "written_by": [
        "lenin"
      ],
      "written_at": "1914-05",
      "written_in": null,
      "first_published_at": "1914-05-10",
      "first_published_in_publication": "真理之路报",
      "first_published_by": null,
      "original_language": "ru",
      "source_collection": "列宁全集",
      "source_volume": 20,
      "source_pages": null,
      "translation_publisher": null,
      "raw_text": "中文马克思主义文库 -> 列宁\n载于1914年5月10日选自《列宁全集》第20卷"
    },
    "evidence": [
      {
        "claim": "本文写于1914年5月，署名弗·伊·，发表于《真理之路报》。",
        "source": "provenance_block",
        "quote": "载于1914年5月10日选自《列宁全集》第20卷\n署名：弗·伊·\n按《真理之路报》原文刊印"
      },
      {
        "claim": "文章论战对象包括崩得分子、取消派分子、民粹派分子以及“钟声”杂志的作者们。",
        "source": "provenance_block",
        "quote": "让那些庸俗的民族主义者、崩得分子、取消派分子、民粹派分子和“钟声”杂志的作者们，去公开捍卫他们资产阶级的精致的民族主义原则吧！"
      },
      {
        "claim": "文章批评了符·奥·女士在《北方工人报》上的观点。",
        "source": "provenance_block",
        "quote": "不要象符·奥·女士在“北方工人报”第35号上那样欺骗工人，她硬要读者相信，似乎“拥护真理报”是否认用本民族语言来教学的！！"
      }
    ]
  }
}