{
  "_prompt_version": "marxist-v0.1-2026-04-30",
  "n": 4,
  "annotation": {
    "gist": "本段是曼彻斯特学派（自由贸易派）从生产成本角度批判旧制度，列举王权、贵族、教会等为“非生产性费用”，主张推翻以建立纯粹的资产阶级共和国。",
    "plain_rewrite": "王权及其奢华的宫廷生活、王室开销和侍从人员，难道不是生产的额外开销吗？没有王权，国家照样能生产和交换产品。所以，必须推翻王位！贵族那些薪水高又清闲的职位，还有上议院——这些又算什么呢？都是生产的额外开销。那庞大的常备军呢？也是生产的额外开销。殖民地呢？同样是生产的额外开销。还有教会，连同它通过掠夺和募捐积累的财富呢？也是生产的额外开销。不如让神甫们自由竞争，人们愿意给多少钱就给多少钱。那庞大臃肿的英国司法机构，还有它的大法官法庭，又是什么呢？同样是生产的额外开销。民族之间的战争呢？也是生产的额外开销。英国如果能与其他民族和平相处，就能以更低的成本来剥削它们。",
    "block_type": "author_text",
    "length_policy": "normal_paragraph",
    "sentences": [
      {
        "sid": "p4s1",
        "plain": "王权及其奢华的宫廷生活、王室开销和侍从人员，难道不是生产的额外开销吗？",
        "speaker": "author",
        "stance": "self",
        "notes": [
          {
            "surface": "王权",
            "type": "concept",
            "target": null,
            "modern": "指英国君主制及其相关开销。",
            "highlight": "term"
          },
          {
            "surface": "faux frais",
            "type": "concept",
            "target": null,
            "modern": "法语词，意为“非生产性费用”或“额外开销”，指不直接创造物质财富的开支。",
            "highlight": "term"
          }
        ]
      },
      {
        "sid": "p4s2",
        "plain": "没有王权，国家照样能生产和交换产品。所以，必须推翻王位！",
        "speaker": "author",
        "stance": "self",
        "notes": []
      },
      {
        "sid": "p4s3",
        "plain": "贵族那些薪水高又清闲的职位，还有上议院——这些又算什么呢？",
        "speaker": "author",
        "stance": "self",
        "notes": []
      },
      {
        "sid": "p4s4",
        "plain": "都是生产的额外开销。那庞大的常备军呢？",
        "speaker": "author",
        "stance": "self",
        "notes": []
      },
      {
        "sid": "p4s5",
        "plain": "也是生产的额外开销。殖民地呢？",
        "speaker": "author",
        "stance": "self",
        "notes": []
      },
      {
        "sid": "p4s6",
        "plain": "同样是生产的额外开销。",
        "speaker": "author",
        "stance": "self",
        "notes": []
      },
      {
        "sid": "p4s7",
        "plain": "还有教会，连同它通过掠夺和募捐积累的财富呢？",
        "speaker": "author",
        "stance": "self",
        "notes": []
      },
      {
        "sid": "p4s8",
        "plain": "也是生产的额外开销。",
        "speaker": "author",
        "stance": "self",
        "notes": []
      },
      {
        "sid": "p4s9",
        "plain": "不如让神甫们自由竞争，人们愿意给多少钱就给多少钱。",
        "speaker": "author",
        "stance": "self",
        "notes": []
      },
      {
        "sid": "p4s10",
        "plain": "那庞大臃肿的英国司法机构，还有它的大法官法庭，又是什么呢？",
        "speaker": "author",
        "stance": "self",
        "notes": [
          {
            "surface": "大法官法庭",
            "type": "org",
            "target": null,
            "modern": "指英国历史上负责衡平法事务的司法机构，此处泛指旧司法体系。",
            "highlight": null
          }
        ]
      },
      {
        "sid": "p4s11",
        "plain": "同样是生产的额外开销。",
        "speaker": "author",
        "stance": "self",
        "notes": []
      },
      {
        "sid": "p4s12",
        "plain": "民族之间的战争呢？",
        "speaker": "author",
        "stance": "self",
        "notes": []
      },
      {
        "sid": "p4s13",
        "plain": "也是生产的额外开销。",
        "speaker": "author",
        "stance": "self",
        "notes": []
      },
      {
        "sid": "p4s14",
        "plain": "英国如果能与其他民族和平相处，就能以更低的成本来剥削它们。",
        "speaker": "author",
        "stance": "self",
        "notes": [
          {
            "surface": "剥削",
            "type": "concept",
            "target": null,
            "modern": "指资产阶级对其他民族的经济掠夺和不平等交换。",
            "highlight": "term"
          }
        ]
      }
    ]
  }
}