{
  "_prompt_version": "marxist-v0.1-2026-04-30",
  "n": 35,
  "annotation": {
    "gist": "本段马克思转述并批判格雷格先生的观点，指出谷物法通过迫使资本投向劣等地，导致谷物价格上涨，进而推高地租。",
    "plain_rewrite": "他承认，谷物法之所以会导致地租上涨，仅仅是因为谷物法会引起谷物价格上涨。而谷物法之所以会引起谷物价格上涨，正是由于谷物法会迫使资本投向劣等地。这一点很容易说明。",
    "block_type": "author_text",
    "length_policy": "normal_paragraph",
    "sentences": [
      {
        "sid": "p35s1",
        "plain": "他承认，谷物法之所以会导致地租上涨，仅仅是因为谷物法会引起谷物价格上涨。而谷物法之所以会引起谷物价格上涨，正是由于谷物法会迫使资本投向劣等地。这一点很容易说明。",
        "speaker": "quoted_opponent",
        "stance": "criticized",
        "notes": [
          {
            "surface": "他",
            "type": "person",
            "target": null,
            "modern": "指大厂主格雷格先生，自由贸易派的代表人物，前文提到的第三位获奖者。",
            "highlight": "polemic"
          },
          {
            "surface": "谷物法",
            "type": "concept",
            "target": null,
            "modern": "19世纪英国限制谷物进口的法律，旨在保护地主利益，是当时政治经济论战的焦点。",
            "highlight": "term"
          },
          {
            "surface": "地租",
            "type": "concept",
            "target": null,
            "modern": "土地所有者因出租土地而获得的收入，在马克思理论中与剩余价值分配相关。",
            "highlight": "term"
          },
          {
            "surface": "谷物价格",
            "type": "concept",
            "target": null,
            "modern": "谷物在市场上的销售价格，受供求关系和生产成本影响。",
            "highlight": "term"
          },
          {
            "surface": "资本",
            "type": "concept",
            "target": null,
            "modern": "用于生产的资金或资源，在马克思理论中指能够带来剩余价值的价值。",
            "highlight": "term"
          },
          {
            "surface": "劣等地",
            "type": "concept",
            "target": null,
            "modern": "肥力较差、产出较低的土地，开垦和耕种成本较高，是古典政治经济学讨论土地边际生产力的概念。",
            "highlight": "term"
          }
        ]
      }
    ]
  }
}